pijoris/__init__.py
pijoris/main.py
pijoris-1.0.2.dist-info/METADATA
pijoris-1.0.2.dist-info/WHEEL
pijoris-1.0.2.dist-info/entry_points.txt
pijoris-1.0.2.dist-info/top_level.txt
pijoris-1.0.2.dist-info/RECORD
