Metadata-Version: 2.1
Name: pijoris
Version: 1.0.2
